type_utils/__init__.py
type_utils/conversions.py
type_utils/require.py
type_utils-1.0.2.dist-info/LICENSE
type_utils-1.0.2.dist-info/METADATA
type_utils-1.0.2.dist-info/WHEEL
type_utils-1.0.2.dist-info/top_level.txt
type_utils-1.0.2.dist-info/RECORD
