Metadata-Version: 2.1
Name: type-utils
Version: 1.0.2
Summary: Type Utils
Home-page: https://github.com/tibotix/type_utils
Author: Tibotix
Author-email: tizian@seehaus.net
Requires-Python: >=3.7, <4
License-File: LICENSE
Provides-Extra: test
Requires-Dist: pytest ; extra == 'test'
